<annotation>
	<folder>30-李航</folder>
	<filename>30LH-89864_640x480_1771.bmp</filename>
	<relpath>..\..\30-李航\30LH-89864_640x480_1771.bmp</relpath>
	<source>
		<database>Unknown</database>
	</source>
	<size>
		<width>640</width>
		<height>480</height>
		<depth>1</depth>
	</size>
	<segmented>0</segmented>
	<object>
		<name>carpet</name>
		<pose>Unspecified</pose>
		<truncated>0</truncated>
		<difficult>0</difficult>
		<bndbox>
			<xmin>169</xmin>
			<ymin>336</ymin>
			<xmax>398</xmax>
			<ymax>358</ymax>
		</bndbox>
	</object>
</annotation>
