<annotation>
	<folder>31-关鑫</folder>
	<filename>31GX-50279472_640x480_1492337.bmp</filename>
	<relpath>..\..\31-关鑫\31GX-50279472_640x480_1492337.bmp</relpath>
	<source>
		<database>Unknown</database>
	</source>
	<size>
		<width>640</width>
		<height>480</height>
		<depth>1</depth>
	</size>
	<segmented>0</segmented>
	<object>
		<name>scale</name>
		<pose>Unspecified</pose>
		<truncated>0</truncated>
		<difficult>0</difficult>
		<bndbox>
			<xmin>443</xmin>
			<ymin>344</ymin>
			<xmax>524</xmax>
			<ymax>363</ymax>
		</bndbox>
	</object>
</annotation>
